rubisco/__init__.py
rubisco/__main__.py
rubisco/config.py
rubisco/cli/__init__.py
rubisco/cli/input.py
rubisco/cli/output.py
rubisco/cli/main/__init__.py
rubisco/cli/main/__main__.py
rubisco/cli/main/arg_parser.py
rubisco/cli/main/help_formatter.py
rubisco/cli/main/ktrigger.py
rubisco/cli/main/log_cleaner.py
rubisco/cli/main/main.py
rubisco/cli/main/project_config.py
rubisco/cli/main/version_action.py
rubisco/envutils/__init__.py
rubisco/envutils/env.py
rubisco/envutils/env_db.py
rubisco/envutils/packages.py
rubisco/envutils/pip.py
rubisco/envutils/utils.py
rubisco/kernel/__init__.py
rubisco/kernel/config_file.py
rubisco/kernel/git.py
rubisco/kernel/mirrorlist.py
rubisco/kernel/project_config.py
rubisco/kernel/workflow.py
rubisco/lib/__init__.py
rubisco/lib/archive.py
rubisco/lib/command.py
rubisco/lib/exceptions.py
rubisco/lib/fileutil.py
rubisco/lib/l10n.py
rubisco/lib/l10n_lang_names.py
rubisco/lib/load_module.py
rubisco/lib/log.py
rubisco/lib/pathlib.py
rubisco/lib/process.py
rubisco/lib/speedtest.py
rubisco/lib/sqlite_strerror.py
rubisco/lib/variable.py
rubisco/lib/version.py
rubisco/lib/wget.py
rubisco/shared/__init__.py
rubisco/shared/extension.py
rubisco/shared/ktrigger.py
rubisco-0.1.0.post0.dist-info/METADATA
rubisco-0.1.0.post0.dist-info/WHEEL
rubisco-0.1.0.post0.dist-info/entry_points.txt
rubisco-0.1.0.post0.dist-info/licenses/LICENSE
rubisco-0.1.0.post0.dist-info/RECORD
