Metadata-Version: 2.3
Name: rubisco
Version: 0.1.0.post0
Summary: C+++ Repository Utilities.
Project-URL: Homepage, https://github.com/cppp-project/rubisco
Author-email: ChenPi11 <wushengwuxi-msctinoulk@outlook.com>
License:                     GNU GENERAL PUBLIC LICENSE
Classifier: License :: OSI Approved :: GNU General Public License v3 (GPLv3)
Classifier: Operating System :: OS Independent
Classifier: Programming Language :: Python :: 3
Requires-Python: >=3.10
Requires-Dist: aiohttp>=3.5.4
Requires-Dist: colorama>=0.3.9
Requires-Dist: json-five>=0.5.1
Requires-Dist: py7zr>=0.16.1
Requires-Dist: pyyaml>=5.4.1
Requires-Dist: requests>=2.18.4
Requires-Dist: rich-argparse>=1.0.0
Requires-Dist: rich>=6.2.0
